thinkhub/__init__.py
thinkhub/chat/__init__.py
thinkhub/chat/anthropic_chat.py
thinkhub/chat/base.py
thinkhub/chat/exceptions.py
thinkhub/chat/gemini_chat.py
thinkhub/chat/openai_chat.py
thinkhub/chat/utils.py
thinkhub/config_loader.py
thinkhub/exceptions.py
thinkhub/transcription/__init__.py
thinkhub/transcription/base.py
thinkhub/transcription/exceptions.py
thinkhub/transcription/google_transcription.py
thinkhub/transcription/openai_transcription.py
thinkhub/utils.py
thinkhub-0.4.2.dist-info/LICENSE
thinkhub-0.4.2.dist-info/METADATA
thinkhub-0.4.2.dist-info/WHEEL
thinkhub-0.4.2.dist-info/RECORD
