Metadata-Version: 2.1
Name: thinkhub
Version: 0.4.2
Summary: ThinkHub is a versatile Python framework that provides a unified interface for interacting with multiple AI services, such as chat and transcription. It simplifies the integration process and allows developers to extend its functionality by creating and registering custom plugins. ThinkHub is designed for flexibility and scalability, making it an ideal choice for projects that rely on AI-driven services.
Home-page: https://github.com/mfenerich/thinkhub.git
License: MIT
Keywords: AI,chat,transcription,framework
Author: Marcel Fenerich
Author-email: marcel@feneri.ch
Requires-Python: >=3.11,<4.0
Classifier: Intended Audience :: Developers
Classifier: License :: OSI Approved :: MIT License
Classifier: Programming Language :: Python :: 3
Classifier: Programming Language :: Python :: 3.11
Classifier: Programming Language :: Python :: 3.12
Classifier: Topic :: Software Development :: Libraries
Provides-Extra: all
Provides-Extra: anthropic
Provides-Extra: google
Provides-Extra: google-generativeai
Provides-Extra: openai
Requires-Dist: aiofiles (>=24.1.0,<25.0.0)
Requires-Dist: anthropic (>=0.45,<0.50) ; extra == "anthropic" or extra == "all"
Requires-Dist: decouple (>=0.0.7,<0.0.8)
Requires-Dist: google-cloud-speech (>=2.30.0,<3.0.0) ; extra == "google" or extra == "all"
Requires-Dist: google-cloud-storage (>=2.19,<4.0) ; extra == "google" or extra == "all"
Requires-Dist: google-generativeai (>=0.8.4,<0.9.0) ; extra == "google-generativeai" or extra == "all"
Requires-Dist: openai (>=1.60.1,<2.0.0) ; extra == "openai" or extra == "all"
Requires-Dist: pillow (>=11.1.0,<12.0.0) ; extra == "google-generativeai" or extra == "all"
Requires-Dist: pydub (>=0.25.1,<0.26.0)
Requires-Dist: tenacity (>=9.0.0,<10.0.0)
Requires-Dist: tiktoken (>=0.8,<0.10) ; extra == "openai" or extra == "all"
Project-URL: Repository, https://github.com/mfenerich/thinkhub.git
